chiron/__init__.py
chiron/_version.py
chiron/chiron_client.py
chiron/chiron_cnn_train.py
chiron/chiron_eval.py
chiron/chiron_eval_test.py
chiron/chiron_input.py
chiron/chiron_label.py
chiron/chiron_model.py
chiron/chiron_multi_gpu_train.py
chiron/chiron_queue_input.py
chiron/chiron_rcnn_train.py
chiron/chiron_train.py
chiron/cnn.py
chiron/entry.py
chiron/export_test.py
chiron/grid_search.py
chiron/load_run_test.py
chiron/rnn.py
chiron/train_test.py
chiron/example_data/DNA/read1.fast5
chiron/example_data/DNA/read2.fast5
chiron/example_data/DNA/read3.fast5
chiron/example_data/DNA/read4.fast5
chiron/example_data/DNA/read5.fast5
chiron/example_data/DNA/output/meta/.meta
chiron/example_data/DNA/output/meta/all.meta
chiron/example_data/DNA/output/meta/read1.meta
chiron/example_data/DNA/output/meta/read2.meta
chiron/example_data/DNA/output/meta/read3.meta
chiron/example_data/DNA/output/meta/read4.meta
chiron/example_data/DNA/output/meta/read5.meta
chiron/example_data/DNA/output/raw/read1.signal
chiron/example_data/DNA/output/raw/read2.signal
chiron/example_data/DNA/output/raw/read3.signal
chiron/example_data/DNA/output/raw/read4.signal
chiron/example_data/DNA/output/raw/read5.signal
chiron/example_data/DNA/output/result/read1.fastq
chiron/example_data/DNA/output/result/read2.fastq
chiron/example_data/DNA/output/result/read3.fastq
chiron/example_data/DNA/output/result/read4.fastq
chiron/example_data/DNA/output/result/read5.fastq
chiron/example_data/DNA/output/segments/read1.fastq
chiron/example_data/DNA/output/segments/read2.fastq
chiron/example_data/DNA/output/segments/read3.fastq
chiron/example_data/DNA/output/segments/read4.fastq
chiron/example_data/DNA/output/segments/read5.fastq
chiron/example_data/RNA/makeson_PC_20170907_FAH20216_MN17284_mux_scan_MA470_R94_NA_122878_09_07_17_25325_read_100_ch_201_strand.fast5
chiron/example_data/RNA/makeson_PC_20170907_FAH20216_MN17284_mux_scan_MA470_R94_NA_122878_09_07_17_25325_read_100_ch_328_strand.fast5
chiron-0.6.1.1.dist-info/LICENSE.md
chiron-0.6.1.1.dist-info/METADATA
chiron-0.6.1.1.dist-info/WHEEL
chiron-0.6.1.1.dist-info/entry_points.txt
chiron-0.6.1.1.dist-info/top_level.txt
chiron-0.6.1.1.dist-info/RECORD
